psaspotter/__init__.py
psaspotter/__main__.py
psaspotter/apis-all.json
psaspotter/apis-main.json
psaspotter/apis-mobile.json
psaspotter/apis-proprietary.json
psaspotter/apis-standards.json
psaspotter/apis-unix-like.json
psaspotter/apis-webassembly.json
psaspotter/availability.json
psaspotter/batch.py
psaspotter/capture.py
psaspotter/extract.py
psaspotter/get_repo.py
psaspotter/main.py
psaspotter/projects.py
psaspotter-0.0.10.dist-info/LICENSE.txt
psaspotter-0.0.10.dist-info/METADATA
psaspotter-0.0.10.dist-info/WHEEL
psaspotter-0.0.10.dist-info/entry_points.txt
psaspotter-0.0.10.dist-info/top_level.txt
psaspotter-0.0.10.dist-info/zip-safe
psaspotter-0.0.10.dist-info/RECORD
