Metadata-Version: 2.1
Name: psaspotter
Version: 0.0.10
Summary: A tool for extracting of Platform-Specific APIs
Home-page: https://github.com/ricardojob/psaspotter
Author: Ricardo Job
License: MIT
Keywords: platform-specific api detect tool
Classifier: License :: OSI Approved :: MIT License
Classifier: Topic :: Education :: Testing
Classifier: Topic :: Software Development :: Libraries :: Python Modules
Classifier: Development Status :: 5 - Production/Stable
Classifier: Intended Audience :: Education
Classifier: Intended Audience :: Developers
Classifier: Intended Audience :: Information Technology
Classifier: Intended Audience :: Science/Research
Classifier: Programming Language :: Python :: 3 :: Only
Classifier: Programming Language :: Python :: 3.8
Classifier: Programming Language :: Python :: 3.9
Classifier: Programming Language :: Python :: 3.10
Classifier: Programming Language :: Python :: 3.11
Requires-Python: ~= 3.8
License-File: LICENSE.txt
Requires-Dist: click~=8.1.7
Requires-Dist: jsonschema~=4.21.0
Requires-Dist: smmap~=5.0.1
Requires-Dist: coverage~=6.5.0
Requires-Dist: pytest
Requires-Dist: pygments
Requires-Dist: pydriller
Requires-Dist: requests
